azure/__init__.py
azure/cli/__init__.py
azure/cli/command_modules/__init__.py
azure/cli/command_modules/hdinsight/__init__.py
azure/cli/command_modules/hdinsight/_client_factory.py
azure/cli/command_modules/hdinsight/_completers.py
azure/cli/command_modules/hdinsight/_help.py
azure/cli/command_modules/hdinsight/_params.py
azure/cli/command_modules/hdinsight/_validators.py
azure/cli/command_modules/hdinsight/commands.py
azure/cli/command_modules/hdinsight/custom.py
azure/cli/command_modules/hdinsight/util.py
opal_azure_cli_hdinsight-0.3.8.dist-info/METADATA
opal_azure_cli_hdinsight-0.3.8.dist-info/WHEEL
opal_azure_cli_hdinsight-0.3.8.dist-info/top_level.txt
opal_azure_cli_hdinsight-0.3.8.dist-info/RECORD
